aws_sm/__init__.py
aws_sm/base.py
aws_sm-1.3.0.dist-info/LICENSE
aws_sm-1.3.0.dist-info/METADATA
aws_sm-1.3.0.dist-info/WHEEL
aws_sm-1.3.0.dist-info/top_level.txt
aws_sm-1.3.0.dist-info/RECORD
