Metadata-Version: 2.1
Name: aws-sm
Version: 1.3.0
Summary: A Python wrapper around the AWS Secrets Manager using Boto3
Author-email: Jumpei Sakatsu <saka2jp@gmail.com>
License: MIT License
Classifier: Programming Language :: Python :: 3
Classifier: License :: OSI Approved :: MIT License
Classifier: Operating System :: OS Independent
Requires-Python: >=3.8
License-File: LICENSE
Requires-Dist: boto3 ~=1.16
Provides-Extra: dev
Requires-Dist: pytest ; extra == 'dev'
Requires-Dist: flake8 ; extra == 'dev'
Requires-Dist: flake8-isort ; extra == 'dev'
Requires-Dist: flake8-polyfill ; extra == 'dev'
Requires-Dist: radon ; extra == 'dev'
Requires-Dist: twine ; extra == 'dev'
Requires-Dist: pytest-mock ; extra == 'dev'
